AutoRPE/__init__.py
AutoRPE/AdditionalFiles/fortran_intrinsics
AutoRPE/AdditionalFiles/list_of_files_to_keep_unmodified.txt
AutoRPE/AdditionalFiles/list_of_reals_to_keep_unmodified.txt
AutoRPE/AdditionalFiles/read_precisions_template
AutoRPE/Scripts/AdaptNamelists.py
AutoRPE/Scripts/CastFix.py
AutoRPE/Scripts/ImplementMixedtoSources.py
AutoRPE/Scripts/ImplementRPEtoSource.py
AutoRPE/Scripts/MergeUsedVariables.py
AutoRPE/Shared/common_utils.py
AutoRPE/UtilsRPE/AttributeParser.py
AutoRPE/UtilsRPE/BasicFunctions.py
AutoRPE/UtilsRPE/CallManager.py
AutoRPE/UtilsRPE/Error.py
AutoRPE/UtilsRPE/Getter.py
AutoRPE/UtilsRPE/ImplementRPE.py
AutoRPE/UtilsRPE/Inserter.py
AutoRPE/UtilsRPE/MaskCreator.py
AutoRPE/UtilsRPE/NatureDeterminer.py
AutoRPE/UtilsRPE/ObtainSourceFileInfo.py
AutoRPE/UtilsRPE/RegexPattern.py
AutoRPE/UtilsRPE/SourceManager.py
AutoRPE/UtilsRPE/TrackDependency.py
AutoRPE/UtilsRPE/VariablePrecision.py
AutoRPE/UtilsRPE/__init__.py
AutoRPE/UtilsRPE/logger.py
AutoRPE/UtilsRPE/Classes/CaseInsensitiveUtils.py
AutoRPE/UtilsRPE/Classes/Interface.py
AutoRPE/UtilsRPE/Classes/Module.py
AutoRPE/UtilsRPE/Classes/Procedure.py
AutoRPE/UtilsRPE/Classes/SourceFile.py
AutoRPE/UtilsRPE/Classes/Subprogram.py
AutoRPE/UtilsRPE/Classes/Variable.py
AutoRPE/UtilsRPE/Classes/Vault.py
AutoRPE/UtilsRPE/postproc/AddCast.py
AutoRPE/UtilsRPE/postproc/AddCastUtils.py
AutoRPE/UtilsRPE/postproc/Formatter.py
AutoRPE/UtilsRPE/postproc/OriginalFilesManager.py
AutoRPE/UtilsRPE/postproc/UpdateVariablesPrecision.py
AutoRPE/UtilsRPE/preprocess/Preprocessor.py
AutoRPE/UtilsWorkflow/BinaryTree.py
AutoRPE/UtilsWorkflow/BinaryTreeSearch.py
AutoRPE/UtilsWorkflow/Communicator.py
AutoRPE/UtilsWorkflow/ExceptionManager.py
AutoRPE/UtilsWorkflow/Job.py
AutoRPE/UtilsWorkflow/RemoteManager.py
AutoRPE/UtilsWorkflow/__init__.py
AutoRPE-Tests/test.py
AutoRPE-Tests/ImplementRPETests/test_implement_rpe.py
AutoRPE-Tests/ImplementRPETests/sources/Readme.md
AutoRPE-1.0.1.dist-info/LICENSE
AutoRPE-1.0.1.dist-info/METADATA
AutoRPE-1.0.1.dist-info/WHEEL
AutoRPE-1.0.1.dist-info/entry_points.txt
AutoRPE-1.0.1.dist-info/top_level.txt
AutoRPE-1.0.1.dist-info/RECORD
