Metadata-Version: 2.2
Name: AutoRPE
Version: 1.0.1
Summary: AutoRPE is a tool designed to help with the optimization of numerical precision of Computational Science models writen in FORTRAN.
Author-email: Oriol Tintó Prims <oriol.tinto@bsc.es>
License:    Copyright 2024 Barcelona Supercomputing Center
Project-URL: homepage, https://earth.bsc.es/gitlab/ces/hpc-for-es-team/AutoRPE
Project-URL: repository, https://earth.bsc.es/gitlab/ces/hpc-for-es-team/AutoRPE
Project-URL: documentation, https://earth.bsc.es/gitlab/ces/hpc-for-es-team/AutoRPE
Keywords: mixed precision,HPC
Classifier: Programming Language :: Python :: 3
Classifier: Programming Language :: Python :: 3.9
Classifier: Programming Language :: Python :: 3.10
Classifier: Programming Language :: Python :: 3.11
Classifier: Programming Language :: Python :: 3.12
Classifier: Programming Language :: Python :: 3.13
Classifier: License :: OSI Approved :: MIT License
Classifier: Operating System :: OS Independent
Requires-Python: >=3.9
License-File: LICENSE
Requires-Dist: numpy
Requires-Dist: networkx
Requires-Dist: tqdm
Requires-Dist: fprettify
